ieaiaio/__init__.py
ieaiaio/chunkize.py
ieaiaio/ieaiaio.py
ie_a_ia_io-0.1.6.dist-info/LICENSE
ie_a_ia_io-0.1.6.dist-info/METADATA
ie_a_ia_io-0.1.6.dist-info/WHEEL
ie_a_ia_io-0.1.6.dist-info/top_level.txt
ie_a_ia_io-0.1.6.dist-info/RECORD
