Metadata-Version: 2.1
Name: ie-a-ia-io
Version: 0.1.6
Summary: Incredibly basic class for managing simple input/output streams
Home-page: https://gitlab.com/sgarda/ieaiaio_v1
Author: sgarda
Author-email: samueleg.opt@posteo.us
License: UNKNOWN
Platform: UNKNOWN
Classifier: Operating System :: OS Independent
Classifier: Topic :: Utilities
Requires-Python: >=3.5
